[
  {
    "summary": "Shares in Thorn In The Side Limited",
    "category": "Shareholdings",
    "value": null
  },
  {
    "summary": "Shares in Reform UK Party Limited",
    "category": "Shareholdings",
    "value": null
  },
  {
    "summary": "Shares in Farage Media Limited",
    "category": "Shareholdings",
    "value": null
  },
  {
    "summary": "Unpaid directorship of Thorn In The Side Limited",
    "category": "Miscellaneous",
    "value": null
  },
  {
    "summary": "Payment received on 16 July 2024 - £81,607.00",
    "category": "Employment and earnings - Ad hoc payments",
    "value": 81607
  },
  {
    "summary": "Social media work - Google",
    "category": "Employment and earnings",
    "value": null
  },
  {
    "summary": "Payment received on 23 August 2024 - £3,019.32",
    "category": "Employment and earnings - Ad hoc payments",
    "value": 3019.32
  },
  {
    "summary": "Payment received on 13 August 2024 - £622.46",
    "category": "Employment and earnings - Ad hoc payments",
    "value": 622.46
  },
  {
    "summary": "Payment received on 27 August 2024 - £1,155.70",
    "category": "Employment and earnings - Ad hoc payments",
    "value": 1155.7
  },
  {
    "summary": "Payment received on 29 August 2024 - £13,000.00",
    "category": "Employment and earnings - Ad hoc payments",
    "value": 13000
  },
  {
    "summary": "Writing articles - Telegraph media group",
    "category": "Employment and earnings",
    "value": null
  },
  {
    "summary": "Social media work - Meta Platforms",
    "category": "Employment and earnings",
    "value": null
  },
  {
    "summary": "International visit to Belgium between 16 April 2024 and 17 April 2024",
    "category": "Visits outside the UK",
    "value": null
  },
  {
    "summary": "Membership at 5 Hertford Street.",
    "category": "Miscellaneous",
    "value": null
  },
  {
    "summary": "Unpaid Directorship at Farage Media LTD.",
    "category": "Miscellaneous",
    "value": null
  },
  {
    "summary": "Press Gazette Ltd - £475.00",
    "category": "Gifts, benefits and hospitality from UK sources",
    "value": 475,
    "donorName": "Press Gazette Ltd"
  },
  {
    "summary": "Derek Chisora - £2,000.00",
    "category": "Gifts, benefits and hospitality from UK sources",
    "value": 2000,
    "donorName": "Derek Chisora"
  },
  {
    "summary": "TRIC Awards - £445.00",
    "category": "Gifts, benefits and hospitality from UK sources",
    "value": 445,
    "donorName": "TRIC Awards"
  },
  {
    "summary": "Agreement - £4,000.00",
    "category": "Employment and earnings - Ongoing paid employment",
    "value": 4000
  },
  {
    "summary": "Former MEP lifetime access to the European Parliament.",
    "category": "Miscellaneous",
    "value": null
  },
  {
    "summary": "Unpaid Leader at Reform Party UK.",
    "category": "Miscellaneous",
    "value": null
  },
  {
    "summary": "Unpaid Directorship at Reform Party UK.",
    "category": "Miscellaneous",
    "value": null
  },
  {
    "summary": "Property in Tandridge",
    "category": "Land and property (within or outside the UK)",
    "value": null
  },
  {
    "summary": "Payment received on 24 July 2024 - £1,551.29",
    "category": "Employment and earnings - Ad hoc payments",
    "value": 1551.29
  },
  {
    "summary": "Payment received on 23 July 2024 - £11,783.55",
    "category": "Employment and earnings - Ad hoc payments",
    "value": 11783.55
  },
  {
    "summary": "Cameo video recordings - Baron App Inc (Cameo)",
    "category": "Employment and earnings",
    "value": null
  },
  {
    "summary": "Payment received on 31 July 2024 - £16,597.22",
    "category": "Employment and earnings - Ad hoc payments",
    "value": 16597.22
  },
  {
    "summary": "International visit to United States between 17 July 2024 and 19 July 2024",
    "category": "Visits outside the UK",
    "value": null
  },
  {
    "summary": "Social media - X Corp",
    "category": "Employment and earnings",
    "value": null
  },
  {
    "summary": "Speaking engagement - AZ Liberty Network",
    "category": "Employment and earnings",
    "value": null
  },
  {
    "summary": "Payment received on 25 July 2024 - £853.34",
    "category": "Employment and earnings - Ad hoc payments",
    "value": 853.34
  },
  {
    "summary": "Property in Folkestone and Hythe",
    "category": "Land and property (within or outside the UK)",
    "value": null
  },
  {
    "summary": "Presenter - GB News Ltd",
    "category": "Employment and earnings",
    "value": null
  }
]